ctpbee_api/__init__.py
ctpbee_api/ctp/__init__.py
ctpbee_api/ctp/ctp_constant.py
ctpbee_api/ctp/libthostmduserapi_se.so
ctpbee_api/ctp/libthosttraderapi_se.so
ctpbee_api/ctp/thostmduserapi_se.dll
ctpbee_api/ctp/thosttraderapi_se.dll
ctpbee_api/ctp/vnctpmd.cp37-win_amd64.pyd
ctpbee_api/ctp/vnctptd.cp37-win_amd64.pyd
ctpbee_api/ctp/generator/concat.py
ctpbee_api/ctp/generator/const.py
ctpbee_api/ctp/generator/ctp_constant.py
ctpbee_api/ctp/generator/ctp_md_header_define.h
ctpbee_api/ctp/generator/ctp_md_header_function.h
ctpbee_api/ctp/generator/ctp_md_header_on.h
ctpbee_api/ctp/generator/ctp_md_header_process.h
ctpbee_api/ctp/generator/ctp_md_source_function.cpp
ctpbee_api/ctp/generator/ctp_md_source_module.cpp
ctpbee_api/ctp/generator/ctp_md_source_on.cpp
ctpbee_api/ctp/generator/ctp_md_source_process.cpp
ctpbee_api/ctp/generator/ctp_md_source_switch.cpp
ctpbee_api/ctp/generator/ctp_md_source_task.cpp
ctpbee_api/ctp/generator/ctp_struct.py
ctpbee_api/ctp/generator/ctp_td_header_define.h
ctpbee_api/ctp/generator/ctp_td_header_function.h
ctpbee_api/ctp/generator/ctp_td_header_on.h
ctpbee_api/ctp/generator/ctp_td_header_process.h
ctpbee_api/ctp/generator/ctp_td_source_function.cpp
ctpbee_api/ctp/generator/ctp_td_source_module.cpp
ctpbee_api/ctp/generator/ctp_td_source_on.cpp
ctpbee_api/ctp/generator/ctp_td_source_process.cpp
ctpbee_api/ctp/generator/ctp_td_source_switch.cpp
ctpbee_api/ctp/generator/ctp_td_source_task.cpp
ctpbee_api/ctp/generator/ctp_typedef.py
ctpbee_api/ctp/generator/generate_api_functions.py
ctpbee_api/ctp/generator/generate_data_type.py
ctpbee_api/ctp/generator/generate_struct.py
ctpbee_api/ctp/include/mac/ctp/ThostFtdcMdApi.h
ctpbee_api/ctp/include/mac/ctp/ThostFtdcTraderApi.h
ctpbee_api/ctp/include/mac/ctp/ThostFtdcUserApiDataType.h
ctpbee_api/ctp/include/mac/ctp/ThostFtdcUserApiStruct.h
ctpbee_api/ctp/include/mac/pybind11/attr.h
ctpbee_api/ctp/include/mac/pybind11/buffer_info.h
ctpbee_api/ctp/include/mac/pybind11/cast.h
ctpbee_api-0.47.dist-info/METADATA
ctpbee_api-0.47.dist-info/WHEEL
ctpbee_api-0.47.dist-info/top_level.txt
ctpbee_api-0.47.dist-info/RECORD
