Metadata-Version: 2.1
Name: ctpbee-api
Version: 0.47
Summary: Trading API support for China Future
Home-page: https://github.com/ctpbee/ctpbee_api
Author: somewheve
Author-email: somewheve@gmail.com
License: MIT
Platform: Windows
Platform: Linux
Platform: Mac OS-X
